volosti_gui_kivy/__init__.py
volosti_gui_kivy/py.typed
volosti_gui_kivy-0.1.dev0.dist-info/LICENSE
volosti_gui_kivy-0.1.dev0.dist-info/WHEEL
volosti_gui_kivy-0.1.dev0.dist-info/METADATA
volosti_gui_kivy-0.1.dev0.dist-info/RECORD
